{
  "defaultColDef": {
    "width": 150,
    "sortable": true,
    "sortingOrder": [
      "desc",
      "asc"
    ],
    "resizable": true
  },
  "columnDefs": [
    {
      "field": "row_header",
      "headerName": "Treebank",
      "pinned": "left",
      "lockPinned": true
    },
    {
      "field": "noun_subj",
      "headerName": "noun_subj",
      "request": "pattern {GOV-[subj]->DEP;GOV [upos=AUX|VERB];DEP[ExtPos=NOUN/upos=NOUN,!Title, !InTitle]}"
    },
    {
      "field": "pron_subj",
      "headerName": "pron_subj",
      "request": "pattern {GOV-[subj]->DEP;GOV [upos=AUX|VERB];DEP[ExtPos=PRON/upos=PRON,!Title, !InTitle]}"
    },
    {
      "field": "propn_subj",
      "headerName": "propn_subj",
      "request": "pattern {GOV-[subj]->DEP;GOV [upos=AUX|VERB];DEP[ExtPos=PROPN/upos=PROPN,!Title, !InTitle]}"
    },
    {
      "field": "num_subj",
      "headerName": "num_subj",
      "request": "pattern {GOV-[subj]->DEP;GOV [upos=AUX|VERB];DEP[ExtPos=NUM/upos=NUM,!Title, !InTitle]}"
    },
    {
      "field": "infinitiv_subj",
      "headerName": "infinitiv_subj",
      "request": "pattern {GOV-[subj]->DEP;GOV [upos=AUX|VERB];DEP[upos=VERB|AUX, VerbForm=Inf,!Title, !InTitle]}"
    },
    {
      "field": "title_subj",
      "headerName": "title_subj",
      "request": "pattern {GOV-[subj]->DEP;DEP [Title=Yes/InTitle=Yes]}"
    },
    {
      "field": "adverbial_subj",
      "headerName": "adverbial_subj",
      "request": "pattern {GOV-[subj]->DEP;DEP [upos=ADV, ExtPos=PRON, !Title, !InTitle]}"
    }
  ],
  "rowData": [
    {
      "row_header": "SUD_French-GSD@latest",
      "noun_subj": 7387,
      "pron_subj": 8230,
      "propn_subj": 3132,
      "num_subj": 29,
      "infinitiv_subj": 19,
      "title_subj": 75,
      "adverbial_subj": 37
    },
    {
      "row_header": "SUD_French-ParisStories@latest",
      "noun_subj": 122,
      "pron_subj": 3828,
      "propn_subj": 12,
      "num_subj": 0,
      "infinitiv_subj": 0,
      "title_subj": 0,
      "adverbial_subj": 0
    },
    {
      "row_header": "SUD_French-Rhapsodie@latest",
      "noun_subj": 316,
      "pron_subj": 2976,
      "propn_subj": 88,
      "num_subj": 1,
      "infinitiv_subj": 2,
      "title_subj": 3,
      "adverbial_subj": 2
    }
  ]
}
